README.rst
setup.cfg
setup.py
ebcdic/__init__.py
ebcdic/cp037.py
ebcdic/cp1025.py
ebcdic/cp1047.py
ebcdic/cp1097.py
ebcdic/cp1112.py
ebcdic/cp1122.py
ebcdic/cp1123.py
ebcdic/cp1140.py
ebcdic/cp1141.py
ebcdic/cp1142.py
ebcdic/cp1143.py
ebcdic/cp1144.py
ebcdic/cp1145.py
ebcdic/cp1146.py
ebcdic/cp1147.py
ebcdic/cp1148.py
ebcdic/cp1148ms.py
ebcdic/cp1149.py
ebcdic/cp273.py
ebcdic/cp277.py
ebcdic/cp278.py
ebcdic/cp280.py
ebcdic/cp284.py
ebcdic/cp285.py
ebcdic/cp290.py
ebcdic/cp297.py
ebcdic/cp420.py
ebcdic/cp424.py
ebcdic/cp500.py
ebcdic/cp500ms.py
ebcdic/cp833.py
ebcdic/cp838.py
ebcdic/cp870.py
ebcdic/cp871.py
ebcdic/cp875.py
ebcdic.egg-info/PKG-INFO
ebcdic.egg-info/SOURCES.txt
ebcdic.egg-info/dependency_links.txt
ebcdic.egg-info/top_level.txt